condensa/__init__.py
condensa/cfg.py
condensa/compressor.py
condensa/data.py
condensa/delta.py
condensa/dtypes.py
condensa/finetune.py
condensa/functional.py
condensa/lr.py
condensa/pi.py
condensa/schemes.py
condensa/tensor.py
condensa/type_enums.py
condensa/util.py
condensa/version.py
condensa/opt/__init__.py
condensa/opt/direct/__init__.py
condensa/opt/direct/dc.py
condensa/opt/lc/__init__.py
condensa/opt/lc/adam.py
condensa/opt/lc/lc.py
condensa/opt/lc/sgd.py
condensa-0.5.0b0.dist-info/LICENSE
condensa-0.5.0b0.dist-info/METADATA
condensa-0.5.0b0.dist-info/WHEEL
condensa-0.5.0b0.dist-info/top_level.txt
condensa-0.5.0b0.dist-info/RECORD
