Metadata-Version: 2.1
Name: condensa
Version: 0.5.0b0
Summary: Condensa Programmable Model Compression Framework
Home-page: https://github.com/NVLabs/condensa
Author: Saurav Muralidharan
Author-email: sauravm@nvidia.com
License: Apache License 2.0
Keywords: compression,quantization,pruning
Platform: UNKNOWN
Classifier: Development Status :: 4 - Beta
Classifier: Intended Audience :: Developers
Classifier: Intended Audience :: Science/Research
Classifier: Topic :: Software Development :: Build Tools
Classifier: License :: OSI Approved :: Apache Software License
Classifier: Programming Language :: Python :: 3
Classifier: Topic :: Software Development :: Libraries
Classifier: Topic :: Scientific/Engineering :: Artificial Intelligence
Requires-Dist: numpy
Requires-Dist: torch (>=1.0.0)
Requires-Dist: tqdm
